livekit/plugins/hume/__init__.py
livekit/plugins/hume/log.py
livekit/plugins/hume/py.typed
livekit/plugins/hume/tts.py
livekit/plugins/hume/version.py
livekit_plugins_hume-1.3.11.dist-info/METADATA
livekit_plugins_hume-1.3.11.dist-info/WHEEL
livekit_plugins_hume-1.3.11.dist-info/RECORD
